setup.py
bin/pasta
pasta/__init__.py
pasta/db.py
pasta/filters.py
pasta/tools.py
pasta.egg-info/PKG-INFO
pasta.egg-info/SOURCES.txt
pasta.egg-info/dependency_links.txt
pasta.egg-info/not-zip-safe
pasta.egg-info/requires.txt
pasta.egg-info/top_level.txt