Metadata-Version: 1.0
Name: pasta
Version: 0.2
Summary: The Yangcong Data Requirement ToolKit
Home-page: http://github.com/guanghetv/pasta
Author: ronfe
Author-email: hongfei@guanghe.tv
License: MIT
Platform: UNKNOWN
